encrypt_algorithms/__init__.py
encrypt_algorithms/complex_encryption/__init__.py
encrypt_algorithms/complex_encryption/gronsfeld.py
encrypt_algorithms/complex_encryption/viginere.py
encrypt_algorithms/rsa_encryption/__init__.py
encrypt_algorithms/rsa_encryption/rsa.py
encrypt_algorithms/simple_encryption/__init__.py
encrypt_algorithms/simple_encryption/caesar.py
encrypt_algorithms/simple_encryption/substitution.py
encrypt_algorithms-1.0.0.dist-info/LICENSE.txt
encrypt_algorithms-1.0.0.dist-info/METADATA
encrypt_algorithms-1.0.0.dist-info/WHEEL
encrypt_algorithms-1.0.0.dist-info/top_level.txt
encrypt_algorithms-1.0.0.dist-info/RECORD
