Metadata-Version: 2.1
Name: encrypt_algorithms
Version: 1.0.0
Summary: A library for encryption algorithms, including Grosfeld and Vigenere methods.
Home-page: https://github.com/annyelis/Python_labs/tree/main/encrypt_algorithms
Author: annyelis
Author-email: anutikelis@gmail.com
Classifier: Programming Language :: Python :: 3
Classifier: License :: OSI Approved :: MIT License
Classifier: Operating System :: OS Independent
Requires-Python: >=3.7
License-File: LICENSE.txt
